epidemic_intelligence/__init__.py
epidemic_intelligence/boxplots.py
epidemic_intelligence/importation_plots.py
epidemic_intelligence/processing.py
epidemic_intelligence/fonts/Barlow-Regular.ttf
epidemic_intelligence/fonts/BarlowSemiCondensed-Light.ttf
epidemic_intelligence/fonts/Itim-Regular.ttf
epidemic_intelligence/helper/__init__.py
epidemic_intelligence/helper/helper.py
epidemic_intelligence/templates/__init__.py
epidemic_intelligence/templates/netsi.py
epidemic_intelligence-1.0.1.dist-info/METADATA
epidemic_intelligence-1.0.1.dist-info/WHEEL
epidemic_intelligence-1.0.1.dist-info/licenses/license.txt
epidemic_intelligence-1.0.1.dist-info/RECORD
