Metadata-Version: 2.4
Name: epidemic-intelligence
Version: 1.0.1
Summary: A data visualization package to explore large-scale spatio-temporal simulation data.
Project-URL: Repository, https://github.com/mattk7/epidemic-intelligence
Author-email: Elijah Sandler <sandler.e@northeastern.edu>, Matteo Chinazzi <m.chinazzi@northeastern.edu>
License-File: license.txt
Classifier: License :: OSI Approved :: BSD License
Classifier: Operating System :: OS Independent
Classifier: Programming Language :: Python :: 3
Requires-Python: >=3.8
Requires-Dist: db-dtypes>=1.0.0
Requires-Dist: epiweeks
Requires-Dist: google-cloud-bigquery-storage
Requires-Dist: google-cloud-bigquery>=3.0.0
Requires-Dist: kaleido==0.1.0.post1
Requires-Dist: matplotlib>=3.7.0
Requires-Dist: pandas>=2.1.0
Requires-Dist: plotly>=5.24
